verbump/__init__.py
verbump/cli.py
verbump/constants.py
verbump/git.py
verbump/version.py
verbump-0.2.4.dist-info/METADATA
verbump-0.2.4.dist-info/WHEEL
verbump-0.2.4.dist-info/entry_points.txt
verbump-0.2.4.dist-info/top_level.txt
verbump-0.2.4.dist-info/RECORD
