Metadata-Version: 2.1
Name: verbump
Version: 0.2.4
Summary: Easy version incrementing CLI tool
Home-page: http://github.com/meyt/verbump
Author: MeyT
License: MIT
Keywords: version versioning semver
Platform: UNKNOWN
Classifier: Development Status :: 3 - Alpha
Classifier: Intended Audience :: Developers
Classifier: License :: OSI Approved :: MIT License
Classifier: Operating System :: POSIX :: Linux
Classifier: Operating System :: Unix
Classifier: Programming Language :: Python :: 3.6
Classifier: Programming Language :: Python :: 3.7
Classifier: Programming Language :: Python :: 3.8
Classifier: Programming Language :: Python :: 3.9
Classifier: Topic :: Software Development :: Libraries
Requires-Python: >=3.5
